{"address1": "19300 International Boulevard", "city": "Seattle", "state": "WA", "zip": "98188", "country": "United States", "phone": "206 392 5040", "website": "https://www.alaskaair.com", "industry": "Airlines", "industryDisp": "Airlines", "sector": "Industrials", "longBusinessSummary": "Alaska Air Group, Inc., through its subsidiaries, operated airlines. The company operates through three segments: Mainline, Regional, and Horizon. The company offers scheduled air transportation services on Boeing and Airbus jet aircraft for passengers and cargo throughout the United States, and in parts of Mexico, Costa Rica, and Belize; and for passengers across a shorter distance network within the United States and Canada. Alaska Air Group, Inc. was founded in 1932 and is based in Seattle, Washington.", "fullTimeEmployees": 22978, "companyOfficers": [{"maxAge": 1, "name": "Mr. Benito  Minicucci", "age": 55, "title": "Pres, CEO & Director", "yearBorn": 1967, "fiscalYear": 2022, "totalPay": 2601588, "exercisedValue": 0, "unexercisedValue": 108250}, {"maxAge": 1, "name": "Mr. Shane R. Tackett", "age": 43, "title": "CFO & Exec. VP of Fin.", "yearBorn": 1979, "fiscalYear": 2022, "totalPay": 1697336, "exercisedValue": 0, "unexercisedValue": 21229}, {"maxAge": 1, "name": "Ms. Constance E. von Muehlen", "age": 56, "title": "Exec. VP & COO of Alaska Airlines Inc", "yearBorn": 1966, "fiscalYear": 2022, "totalPay": 1299827, "exercisedValue": 0, "unexercisedValue": 6366}, {"maxAge": 1, "name": "Mr. Andrew R. Harrison", "age": 51, "title": "Exec. VP & Chief Commercial Officer of Alaska Airlines Inc.", "yearBorn": 1971, "fiscalYear": 2022, "totalPay": 1659357, "exercisedValue": 0, "unexercisedValue": 24744}, {"maxAge": 1, "name": "Ms. Andrea L. Schneider", "age": 57, "title": "Sr. VP of People - Alaska Airlines Inc", "yearBorn": 1965, "fiscalYear": 2022, "totalPay": 1188192, "exercisedValue": 0, "unexercisedValue": 42400}, {"maxAge": 1, "name": "Ms. Helvi Kay Sandvik", "age": 64, "title": "Independent Director", "yearBorn": 1958, "fiscalYear": 2022, "totalPay": 105182, "exercisedValue": 0, "unexercisedValue": 0}, {"maxAge": 1, "name": "Ms. Emily  Halverson", "title": "VP of Fin., Controller & Principal Accounting Officer", "exercisedValue": 0, "unexercisedValue": 0}, {"maxAge": 1, "name": "Mr. Lavanya  Sareen", "title": "Managing Director of Investor Relations", "exercisedValue": 0, "unexercisedValue": 0}, {"maxAge": 1, "name": "Mr. Kyle B. Levine", "age": 50, "title": "Chief Ethics & Compliance Officer, Sr. VP of Legal, Gen. Counsel and Corp. Sec.", "yearBorn": 1972, "exercisedValue": 0, "unexercisedValue": 0}, {"maxAge": 1, "name": "Ms. Geni  Venable", "title": "Mang. of Corp. Communication", "exercisedValue": 0, "unexercisedValue": 0}], "auditRisk": 7, "boardRisk": 2, "compensationRisk": 4, "shareHolderRightsRisk": 1, "overallRisk": 2, "governanceEpochDate": 1682899200, "compensationAsOfEpochDate": 1672444800, "maxAge": 86400, "priceHint": 2, "previousClose": 43.9, "open": 44.63, "dayLow": 42.48, "dayHigh": 44.66, "regularMarketPreviousClose": 43.9, "regularMarketOpen": 44.63, "regularMarketDayLow": 42.48, "regularMarketDayHigh": 44.66, "exDividendDate": 1581638400, "payoutRatio": 0.0, "beta": 1.519352, "trailingPE": 89.8125, "forwardPE": 6.071831, "volume": 996761, "regularMarketVolume": 996761, "averageVolume": 1720403, "averageVolume10days": 1544860, "averageDailyVolume10Day": 1544860, "bid": 42.3, "ask": 43.13, "bidSize": 800, "askSize": 1000, "marketCap": 5514243072, "fiftyTwoWeekLow": 37.2, "fiftyTwoWeekHigh": 53.96, "priceToSalesTrailing12Months": 0.542687, "fiftyDayAverage": 43.0266, "twoHundredDayAverage": 44.92615, "trailingAnnualDividendRate": 0.0, "trailingAnnualDividendYield": 0.0, "currency": "USD", "enterpriseValue": 6917291008, "profitMargins": 0.0058099995, "floatShares": 127386522, "sharesOutstanding": 127911000, "sharesShort": 4371177, "sharesShortPriorMonth": 4214737, "sharesShortPreviousMonthDate": 1680220800, "dateShortInterest": 1682640000, "sharesPercentSharesOut": 0.0344, "heldPercentInsiders": 0.00301, "heldPercentInstitutions": 0.84459996, "shortRatio": 2.23, "shortPercentOfFloat": 0.038900003, "impliedSharesOutstanding": 0, "bookValue": 28.992, "priceToBook": 1.486962, "lastFiscalYearEnd": 1672444800, "nextFiscalYearEnd": 1703980800, "mostRecentQuarter": 1680220800, "netIncomeToCommon": 59000000, "trailingEps": 0.48, "forwardEps": 7.1, "pegRatio": 0.28, "lastSplitFactor": "2:1", "lastSplitDate": 1404950400, "enterpriseToRevenue": 0.681, "enterpriseToEbitda": 7.807, "52WeekChange": -0.041693926, "SandP52WeekChange": 0.046755195, "lastDividendValue": 0.375, "lastDividendDate": 1581638400, "exchange": "NYQ", "quoteType": "EQUITY", "symbol": "ALK", "underlyingSymbol": "ALK", "shortName": "Alaska Air Group, Inc.", "longName": "Alaska Air Group, Inc.", "firstTradeDateEpochUtc": 322151400, "timeZoneFullName": "America/New_York", "timeZoneShortName": "EDT", "uuid": "3b198114-06cb-3b50-b1bb-fdb850bdcafa", "messageBoardId": "finmb_248501", "gmtOffSetMilliseconds": -14400000, "currentPrice": 43.11, "targetHighPrice": 75.0, "targetLowPrice": 54.0, "targetMeanPrice": 63.54, "targetMedianPrice": 62.0, "recommendationMean": 1.8, "recommendationKey": "buy", "numberOfAnalystOpinions": 12, "totalCash": 2428999936, "totalCashPerShare": 18.99, "ebitda": 886000000, "totalDebt": 3731000064, "quickRatio": 0.57, "currentRatio": 0.638, "totalRevenue": 10161000448, "debtToEquity": 101.138, "revenuePerShare": 79.985, "returnOnAssets": 0.020569999, "returnOnEquity": 0.01611, "grossProfits": 2357000000, "freeCashflow": -16125000, "operatingCashflow": 1352999936, "revenueGrowth": 0.306, "grossMargins": 0.24722, "ebitdaMargins": 0.0872, "operatingMargins": 0.04616, "financialCurrency": "USD", "trailingPegRatio": null}