{"address1": "24-26, Boulevard d\u2019Avranches", "city": "Luxembourg City", "zip": "1160", "country": "Luxembourg", "phone": "352 47 921", "fax": "352 4792 2675", "website": "https://corporate.arcelormittal.com", "industry": "Steel", "industryDisp": "Steel", "sector": "Basic Materials", "longBusinessSummary": "ArcelorMittal S.A., together with its subsidiaries, operates as integrated steel and mining companies in the Americas, Europe, Asia, and Africa. It offers semi-finished flat products, including slabs; finished flat products comprising plates, hot- and cold-rolled coils and sheets, hot-dipped and electro-galvanized coils and sheets, tinplate, and color coated coils and sheets; semi-finished long products, such as blooms and billets; finished long products consisting of bars, wire-rods, structural sections, rails, sheet piles, and wire-products; and seamless and welded pipes and tubes. The company also provides mining products, such as iron ore lumps, fines, concentrates, pellets, and sinter feeds; and coking and pulverized coal injections coal. It sells its products to various customers in the automotive, appliance, engineering, construction, energy, and machinery industries through a centralized marketing organization, as well as distributors. The company has iron ore mining activities in Brazil, Bosnia, Canada, Kazakhstan, Liberia, Mexico, South Africa, and Ukraine; and coal mining activities in Kazakhstan. ArcelorMittal S.A. was founded in 1976 and is headquartered in Luxembourg City, Luxembourg.", "fullTimeEmployees": 154352, "companyOfficers": [{"maxAge": 1, "name": "Mr. Lakshmi Nivas Mittal B.Com.", "age": 72, "title": "Exec. Chairman", "yearBorn": 1950, "fiscalYear": 2022, "totalPay": 4654000, "exercisedValue": 0, "unexercisedValue": 0}, {"maxAge": 1, "name": "Mr. Aditya  Mittal", "age": 45, "title": "CEO & Director", "yearBorn": 1977, "fiscalYear": 2022, "totalPay": 5211000, "exercisedValue": 0, "unexercisedValue": 0}, {"maxAge": 1, "name": "Mr. Genuino Jose Magalhaes Christino", "age": 50, "title": "Exec. VP & CFO", "yearBorn": 1972, "exercisedValue": 0, "unexercisedValue": 0}, {"maxAge": 1, "name": "Mr. Daniel  Fairclough", "title": "Head of Investor Relations & VP of Corp. Fin.", "exercisedValue": 0, "unexercisedValue": 0}, {"maxAge": 1, "name": "Mr. Henk  Scheffer", "age": 59, "title": "Group Compliance, Data Protection Officer & Company Sec.", "yearBorn": 1963, "exercisedValue": 0, "unexercisedValue": 0}, {"maxAge": 1, "name": "Ms. Nicola  Davidson", "title": "VP and Head of Corp. Communications & Corp. Responsibility", "exercisedValue": 0, "unexercisedValue": 0}, {"maxAge": 1, "name": "Ms. Stephanie  Werner-Dietz", "age": 50, "title": "Exec. VP & Global Head of HR", "yearBorn": 1972, "exercisedValue": 0, "unexercisedValue": 0}, {"maxAge": 1, "name": "Mr. Augustine  Kochuparampil", "age": 70, "title": "VP & CEO of Long Products Europe", "yearBorn": 1952, "exercisedValue": 0, "unexercisedValue": 0}, {"maxAge": 1, "name": "Dr. Gregory  Ludkovsky", "age": 72, "title": "VP and CEO of Global R&D", "yearBorn": 1950, "exercisedValue": 0, "unexercisedValue": 0}, {"maxAge": 1, "name": "Mr. Vijay Krishna Goyal", "age": 50, "title": "Exec. VP & CEO of ArcelorMittal CIS", "yearBorn": 1972, "exercisedValue": 0, "unexercisedValue": 0}], "auditRisk": 3, "boardRisk": 8, "compensationRisk": 2, "shareHolderRightsRisk": 8, "overallRisk": 5, "governanceEpochDate": 1682899200, "compensationAsOfEpochDate": 1672444800, "maxAge": 86400, "priceHint": 2, "previousClose": 27.0, "open": 27.0, "dayLow": 27.0, "dayHigh": 27.0, "regularMarketPreviousClose": 27.0, "regularMarketOpen": 27.0, "regularMarketDayLow": 27.0, "regularMarketDayHigh": 27.0, "dividendRate": 0.44, "dividendYield": 0.0163, "exDividendDate": 1684713600, "payoutRatio": 0.0529, "beta": 1.947388, "trailingPE": 3.7604458, "volume": 2, "regularMarketVolume": 2, "averageVolume": 37501, "averageVolume10days": 7680, "averageDailyVolume10Day": 7680, "bid": 0.0, "ask": 0.0, "bidSize": 0, "askSize": 0, "marketCap": 21780250624, "fiftyTwoWeekLow": 19.55, "fiftyTwoWeekHigh": 32.51, "priceToSalesTrailing12Months": 0.28467566, "fiftyDayAverage": 29.1488, "twoHundredDayAverage": 26.0472, "trailingAnnualDividendRate": 0.44, "trailingAnnualDividendYield": 0.016296295, "currency": "USD", "enterpriseValue": 31445000192, "profitMargins": 0.08199, "floatShares": 525566220, "sharesOutstanding": 786611008, "heldPercentInsiders": 0.37725, "heldPercentInstitutions": 0.21775, "impliedSharesOutstanding": 0, "bookValue": 60.441, "priceToBook": 0.4467166, "lastFiscalYearEnd": 1672444800, "nextFiscalYearEnd": 1703980800, "mostRecentQuarter": 1680220800, "earningsQuarterlyGrowth": -0.734, "netIncomeToCommon": 6272999936, "trailingEps": 7.18, "lastSplitFactor": "1:3", "lastSplitDate": 1495065600, "enterpriseToRevenue": 0.411, "enterpriseToEbitda": 2.901, "52WeekChange": -0.033643544, "SandP52WeekChange": 0.046755195, "lastDividendValue": 0.38, "lastDividendDate": 1652400000, "exchange": "PNK", "quoteType": "EQUITY", "symbol": "AMSYF", "underlyingSymbol": "AMSYF", "shortName": "ARCELORMITTAL", "longName": "ArcelorMittal S.A.", "firstTradeDateEpochUtc": 1231425000, "timeZoneFullName": "America/New_York", "timeZoneShortName": "EDT", "uuid": "b2946ff3-111f-3d76-afa5-ad405b2b2d1d", "messageBoardId": "finmb_364040", "gmtOffSetMilliseconds": -14400000, "currentPrice": 27.0, "recommendationKey": "none", "totalCash": 6289999872, "totalCashPerShare": 7.044, "ebitda": 10837999616, "totalDebt": 11477000192, "quickRatio": 0.494, "currentRatio": 1.566, "totalRevenue": 76509003776, "debtToEquity": 20.45, "revenuePerShare": 86.475, "returnOnAssets": 0.05491, "returnOnEquity": 0.11453, "grossProfits": 14016000000, "freeCashflow": 5612749824, "operatingCashflow": 9118000128, "earningsGrowth": -0.703, "revenueGrowth": -0.153, "grossMargins": 0.14061, "ebitdaMargins": 0.14166, "operatingMargins": 0.11068, "financialCurrency": "USD", "trailingPegRatio": null}