{"address1": "10 Hagavish Street", "city": "Netanya", "zip": "4250708", "country": "Israel", "phone": "972 5 299 89595", "fax": "972 9 860 7986", "website": "https://www.cellcom.co.il", "industry": "Telecom Services", "industryDisp": "Telecom Services", "sector": "Communication Services", "longBusinessSummary": "Cellcom Israel Ltd. provides cellular communications services in Israel. It operates in two segments, Cellular and Fixed-line. The Cellular segment offers cellular communications, and cellular equipment and related services. The Fixed-line segment provides infrastructure and internet access, internet-based television, international telephony, landline telephony services, and transmission services for business customers and for telecommunication operators; and conferencing, cloud computing, and server hosting services, as well as IOT solutions. This segment also sells equipment, such as computers and communication equipment, including servers, routers, and switches, and others; and software and integration of information security products. The company was incorporated in 1994 and is headquartered in Netanya, Israel. Cellcom Israel Ltd. operates as a subsidiary of Discount Investment Corporation Ltd.", "fullTimeEmployees": 2761, "companyOfficers": [{"maxAge": 1, "name": "Mr. Daniel  Sapir", "age": 52, "title": "Chief Exec. Officer", "yearBorn": 1970, "exercisedValue": 0, "unexercisedValue": 0}, {"maxAge": 1, "name": "Mr. Gadi  Attias", "age": 47, "title": "Chief Financial Officer", "yearBorn": 1975, "exercisedValue": 0, "unexercisedValue": 0}, {"maxAge": 1, "name": "Mr. Teimuraz  Romashvili", "age": 43, "title": "VP of Sales & International Activity", "yearBorn": 1979, "exercisedValue": 0, "unexercisedValue": 0}, {"maxAge": 1, "name": "Mr. Nadav  Amsalem", "age": 48, "title": "CEO of Golan Telecom Ltd.", "yearBorn": 1974, "exercisedValue": 0, "unexercisedValue": 0}, {"maxAge": 1, "name": "Mr. Eli  Adadi", "age": 46, "title": "VP Retail & CEO of Dynamica Communications Chain Stores Ltd.", "yearBorn": 1976, "exercisedValue": 0, "unexercisedValue": 0}, {"maxAge": 1, "name": "Mr. Yaniv  Koriat", "age": 46, "title": "VP of Technologies", "yearBorn": 1976, "exercisedValue": 0, "unexercisedValue": 0}, {"maxAge": 1, "name": "Mr. Victor  Malka", "age": 66, "title": "Chief Information Officer", "yearBorn": 1956, "exercisedValue": 0, "unexercisedValue": 0}, {"maxAge": 1, "name": "Elad  Levy", "title": "Investor Relations Mang.", "exercisedValue": 0, "unexercisedValue": 0}, {"maxAge": 1, "name": "Attorney Larisa  Cohen", "age": 45, "title": "VP of Legal & Corp. Sec.", "yearBorn": 1977, "exercisedValue": 0, "unexercisedValue": 0}, {"maxAge": 1, "name": "Daphna Agassi Bar", "age": 52, "title": "VP of Marketing", "yearBorn": 1970, "exercisedValue": 0, "unexercisedValue": 0}], "maxAge": 86400, "priceHint": 4, "previousClose": 3.54, "open": 3.55, "dayLow": 3.55, "dayHigh": 3.62, "regularMarketPreviousClose": 3.54, "regularMarketOpen": 3.55, "regularMarketDayLow": 3.55, "regularMarketDayHigh": 3.62, "exDividendDate": 1385337600, "payoutRatio": 0.0, "beta": 0.696866, "trailingPE": 13.923077, "volume": 691, "regularMarketVolume": 691, "averageVolume": 1305, "averageVolume10days": 790, "averageDailyVolume10Day": 790, "marketCap": 617539456, "fiftyTwoWeekLow": 3.06, "fiftyTwoWeekHigh": 6.37, "fiftyDayAverage": 3.6262, "twoHundredDayAverage": 4.76855, "trailingAnnualDividendRate": 0.0, "trailingAnnualDividendYield": 0.0, "currency": "USD", "enterpriseValue": 585132800, "profitMargins": 0.036510002, "floatShares": 101978404, "sharesOutstanding": 165100992, "sharesShort": 40514, "sharesShortPriorMonth": 42709, "sharesShortPreviousMonthDate": 1607990400, "dateShortInterest": 1610668800, "sharesPercentSharesOut": 0.00029999999, "heldPercentInsiders": 0.56549, "heldPercentInstitutions": 0.27099, "shortRatio": 3.16, "shortPercentOfFloat": 0.0004, "impliedSharesOutstanding": 0, "lastFiscalYearEnd": 1672444800, "nextFiscalYearEnd": 1703980800, "mostRecentQuarter": 1672444800, "earningsQuarterlyGrowth": 1.333, "trailingEps": 0.26, "52WeekChange": -0.34686345, "SandP52WeekChange": 0.046755195, "lastDividendValue": 0.238, "lastDividendDate": 1385337600, "exchange": "PNK", "quoteType": "EQUITY", "symbol": "CELJF", "underlyingSymbol": "CELJF", "shortName": "Cellcom Israel, Ltd.", "longName": "Cellcom Israel Ltd.", "firstTradeDateEpochUtc": 1170772200, "timeZoneFullName": "America/New_York", "timeZoneShortName": "EDT", "uuid": "8e8d6c26-1939-3952-af79-4decbcf5ee02", "messageBoardId": "finmb_606333", "gmtOffSetMilliseconds": -14400000, "currentPrice": 3.62, "recommendationKey": "none", "quickRatio": 0.932, "currentRatio": 1.046, "debtToEquity": 171.578, "returnOnAssets": 0.03759, "returnOnEquity": 0.07801, "grossProfits": 1266000000, "earningsGrowth": 2.006, "revenueGrowth": -0.008, "grossMargins": 0.29442, "ebitdaMargins": 0.19580999, "operatingMargins": 0.0, "financialCurrency": "ILS", "trailingPegRatio": null}