{"address1": "Pacific Centre", "address2": "609 Granville Street Suite 2200 P.O. Box 10337", "city": "Vancouver", "state": "BC", "zip": "V7Y 1H2", "country": "Canada", "website": "https://www.canaccordgenuity.com", "industry": "Capital Markets", "industryDisp": "Capital Markets", "sector": "Financial Services", "longBusinessSummary": "Canaccord Genuity Group Inc., a full-service financial services company, provides investment products, and investment banking and brokerage services to institutional, corporate, and private clients. It operates in two segments, Canaccord Genuity Capital Markets and Canaccord Genuity Wealth Management. The Canaccord Genuity Capital Markets segment offers investment banking, advisory, research, merger and acquisition, sales, and trading services. The Canaccord Genuity Wealth Management segment provides wealth management solutions, and brokerage and financial planning services to individual investors, private clients, charities, and intermediaries. The company operates in North America, the United Kingdom, Europe, Asia, Australia, and the Middle East. Canaccord Genuity Group Inc. was founded in 1950 and is headquartered in Vancouver, Canada.", "fullTimeEmployees": 2850, "companyOfficers": [{"maxAge": 1, "name": "Mr. David Jonathan Kassie", "age": 66, "title": "Exec. Chairman", "yearBorn": 1956, "fiscalYear": 2022, "totalPay": 3150000, "exercisedValue": 0, "unexercisedValue": 0}, {"maxAge": 1, "name": "Mr. Daniel Joseph Daviau", "age": 57, "title": "CEO, Pres & Director", "yearBorn": 1965, "fiscalYear": 2022, "totalPay": 7809083, "exercisedValue": 0, "unexercisedValue": 0}, {"maxAge": 1, "name": "Mr. Donald Duncan MacFayden", "title": "Exec. VP & CFO", "fiscalYear": 2022, "totalPay": 1950000, "exercisedValue": 0, "unexercisedValue": 0}, {"maxAge": 1, "name": "Mr. Jeffrey  Barlow CFA", "title": "Pres of Canaccord Genuity LLC (U.S.)", "fiscalYear": 2022, "totalPay": 5369000, "exercisedValue": 0, "unexercisedValue": 0}, {"maxAge": 1, "name": "Mr. Marcus  Geoffrey John Freeman", "title": "Chief Exec. Officer of Canaccord Genuity Group (Asia-Pacific)", "fiscalYear": 2022, "totalPay": 3591658, "exercisedValue": 0, "unexercisedValue": 0}, {"maxAge": 1, "name": "Mr. Michel  Perera", "title": "Chief Investment Officer", "exercisedValue": 0, "unexercisedValue": 0}, {"maxAge": 1, "name": "Mr. Edward Raye Hirst", "title": "Managing Director Investment Banking", "fiscalYear": 2015, "exercisedValue": 0, "unexercisedValue": 0}, {"maxAge": 1, "name": "Mr. George Henry Miller Garnett", "age": 33, "title": "Director of Corp. Fin.", "yearBorn": 1989, "exercisedValue": 0, "unexercisedValue": 0}, {"maxAge": 1, "name": "Mr. Stuart R. Raftus", "age": 61, "title": "Exec. VP & Chief Admin. Officer", "yearBorn": 1961, "fiscalYear": 2021, "exercisedValue": 0, "unexercisedValue": 0}, {"maxAge": 1, "name": "Ms. Christina  Marinoff", "title": "Sr. VP of Investor Relations & Communications", "exercisedValue": 0, "unexercisedValue": 0}], "auditRisk": 2, "boardRisk": 9, "compensationRisk": 2, "shareHolderRightsRisk": 2, "overallRisk": 4, "governanceEpochDate": 1682899200, "compensationAsOfEpochDate": 1672444800, "maxAge": 86400, "priceHint": 2, "previousClose": 9.01, "open": 8.91, "dayLow": 8.7, "dayHigh": 9.03, "regularMarketPreviousClose": 9.01, "regularMarketOpen": 8.91, "regularMarketDayLow": 8.7, "regularMarketDayHigh": 9.03, "dividendRate": 0.34, "dividendYield": 0.0377, "exDividendDate": 1677110400, "fiveYearAvgDividendYield": 2.15, "beta": 1.615233, "forwardPE": 6.914063, "volume": 644721, "regularMarketVolume": 644721, "averageVolume": 369130, "averageVolume10days": 558510, "averageDailyVolume10Day": 558510, "bid": 8.85, "ask": 8.85, "marketCap": 879527168, "fiftyTwoWeekLow": 6.24, "fiftyTwoWeekHigh": 11.8, "priceToSalesTrailing12Months": 0.570494, "fiftyDayAverage": 10.7658, "twoHundredDayAverage": 9.19475, "trailingAnnualDividendRate": 0.34, "trailingAnnualDividendYield": 0.03773585, "currency": "CAD", "enterpriseValue": 136297792, "profitMargins": -0.01731, "floatShares": 54307884, "sharesOutstanding": 99381600, "sharesShort": 2196956, "sharesShortPriorMonth": 2294307, "sharesShortPreviousMonthDate": 1680220800, "dateShortInterest": 1682640000, "sharesPercentSharesOut": 0.0221, "heldPercentInsiders": 0.08755, "heldPercentInstitutions": 0.11849, "shortRatio": 8.35, "impliedSharesOutstanding": 0, "bookValue": 9.14, "priceToBook": 0.9682713, "lastFiscalYearEnd": 1648684800, "nextFiscalYearEnd": 1680220800, "mostRecentQuarter": 1672444800, "netIncomeToCommon": -36257000, "trailingEps": -0.54, "forwardEps": 1.28, "pegRatio": 0.78, "enterpriseToRevenue": 0.088, "52WeekChange": -0.07873213, "SandP52WeekChange": 0.046755195, "lastDividendValue": 0.085, "lastDividendDate": 1677110400, "exchange": "TOR", "quoteType": "EQUITY", "symbol": "CF.TO", "underlyingSymbol": "CF.TO", "shortName": "CANACCORD GENUITY GROUP INC", "longName": "Canaccord Genuity Group Inc.", "firstTradeDateEpochUtc": 1142001000, "timeZoneFullName": "America/Toronto", "timeZoneShortName": "EDT", "uuid": "0eb8e81f-25de-3c32-964a-deda9d6bc4ec", "messageBoardId": "finmb_8682136", "gmtOffSetMilliseconds": -14400000, "currentPrice": 8.85, "targetHighPrice": 11.5, "targetLowPrice": 9.5, "targetMeanPrice": 10.33, "targetMedianPrice": 10.0, "recommendationMean": 2.7, "recommendationKey": "hold", "numberOfAnalystOpinions": 3, "totalCash": 1671341056, "totalCashPerShare": 19.163, "totalDebt": 467979008, "quickRatio": 1.079, "currentRatio": 1.173, "totalRevenue": 1541693952, "debtToEquity": 34.64, "revenuePerShare": 17.452, "returnOnAssets": 0.0016, "returnOnEquity": 0.00778, "grossProfits": 1845707000, "operatingCashflow": -592166016, "revenueGrowth": -0.323, "grossMargins": 0.884, "ebitdaMargins": 0.0, "operatingMargins": 0.10828, "financialCurrency": "CAD", "trailingPegRatio": null}