{"address1": "Two Exchange Square", "address2": "24th Floor 8 Connaught Place", "city": "Central", "country": "Hong Kong", "phone": "852 2842 4388", "fax": "852 2845 9243", "website": "https://www.firstpacific.com", "industry": "Packaged Foods", "industryDisp": "Packaged Foods", "sector": "Consumer Defensive", "longBusinessSummary": "First Pacific Company Limited, an investment holding company, engages in the consumer food products, telecommunications, infrastructure, and natural resources businesses in the Philippines, Indonesia, Singapore, the Middle East, Africa, and internationally. The company offers a range of telecommunications and digital services, including fiber optic backbone, and fixed line and mobile networks. It also manufactures and distributes a range of food products, including noodles, dairy products, snack foods, food seasonings, nutrition and special foods, beverages, wheat flour, and pasta; breeds seeds; cultivates oil palm, rubber, sugar cane, and other crops; and offers cooking oils, margarines, and shortenings. In addition, the company explores for, mines, and produces gold, copper, and silver; and produces sugar and bioethanol. Further, it is involved in the operation of gas-fired power plant; provision of water distribution, sewerage, and sanitation services; and operation of toll roads, hospitals, and rail lines, as well as provision of logistics services. Additionally, the company engages in distribution of renewable energy related activities. First Pacific Company Limited was founded in 1981 and is headquartered in Central, Hong Kong.", "fullTimeEmployees": 101203, "companyOfficers": [{"maxAge": 1, "name": "Mr. Manuel Velez Pangilinan", "age": 76, "title": "CEO, MD & Exec. Director", "yearBorn": 1946, "fiscalYear": 2021, "totalPay": 7290000, "exercisedValue": 0, "unexercisedValue": 0}, {"maxAge": 1, "name": "Mr. Christopher Huxley  Young", "age": 65, "title": "Exec. Director", "yearBorn": 1957, "fiscalYear": 2021, "totalPay": 2805000, "exercisedValue": 0, "unexercisedValue": 0}, {"maxAge": 1, "name": "Mr. Hon Pong  Ng", "age": 59, "title": "CFO & Associate Director", "yearBorn": 1963, "exercisedValue": 0, "unexercisedValue": 0}, {"maxAge": 1, "name": "Mr. John W.  Ryan", "age": 57, "title": "Chief Investor Relations and Sustainability & Associate Director", "yearBorn": 1965, "exercisedValue": 0, "unexercisedValue": 0}, {"maxAge": 1, "name": "Ms. Wing Man  Chiu", "title": "EVP, Company Sec. & Gen. Counsel", "exercisedValue": 0, "unexercisedValue": 0}, {"maxAge": 1, "name": "Ms. S. K.  Cheung", "age": 58, "title": "VP of Group Corp. Communications", "yearBorn": 1964, "exercisedValue": 0, "unexercisedValue": 0}, {"maxAge": 1, "name": "Mr. Stanley H.  Yang", "age": 45, "title": "Exec. VP & Head of Group Corp. Devel.", "yearBorn": 1977, "exercisedValue": 0, "unexercisedValue": 0}, {"maxAge": 1, "name": "Mr. T. H.  Lin", "age": 52, "title": "Exec. VP of Group Treasury & Tax and Group HR", "yearBorn": 1970, "exercisedValue": 0, "unexercisedValue": 0}, {"maxAge": 1, "name": "Mr. Ping Cheung  Chan", "age": 52, "title": "Exec. VP &  Group Financial Controller", "yearBorn": 1970, "exercisedValue": 0, "unexercisedValue": 0}, {"maxAge": 1, "name": "Ms. W.Y.  Lau", "age": 55, "title": "VP & Company Secretariat", "yearBorn": 1967, "exercisedValue": 0, "unexercisedValue": 0}], "auditRisk": 2, "boardRisk": 4, "compensationRisk": 3, "shareHolderRightsRisk": 4, "overallRisk": 3, "governanceEpochDate": 1682899200, "compensationAsOfEpochDate": 1640908800, "maxAge": 86400, "priceHint": 4, "previousClose": 0.3653, "open": 0.3653, "dayLow": 0.3653, "dayHigh": 0.3653, "regularMarketPreviousClose": 0.3653, "regularMarketOpen": 0.3653, "regularMarketDayLow": 0.3653, "regularMarketDayHigh": 0.3653, "dividendRate": 0.03, "dividendYield": 0.0802, "exDividendDate": 1687219200, "payoutRatio": 0.2842, "fiveYearAvgDividendYield": 5.11, "beta": 1.07234, "trailingPE": 4.058889, "volume": 102, "regularMarketVolume": 102, "averageVolume": 18820, "averageVolume10days": 25710, "averageDailyVolume10Day": 25710, "bid": 0.0, "ask": 0.0, "bidSize": 0, "askSize": 0, "marketCap": 1549478400, "fiftyTwoWeekLow": 0.26, "fiftyTwoWeekHigh": 0.46, "priceToSalesTrailing12Months": 0.15036327, "fiftyDayAverage": 0.3158, "twoHundredDayAverage": 0.33075, "trailingAnnualDividendRate": 0.028, "trailingAnnualDividendYield": 0.07664933, "currency": "USD", "enterpriseValue": 17242531840, "profitMargins": 0.038, "floatShares": 2210416149, "sharesOutstanding": 4241659904, "heldPercentInsiders": 0.47707, "heldPercentInstitutions": 0.22389999, "impliedSharesOutstanding": 0, "bookValue": 0.778, "priceToBook": 0.4695373, "lastFiscalYearEnd": 1672444800, "nextFiscalYearEnd": 1703980800, "mostRecentQuarter": 1672444800, "earningsQuarterlyGrowth": -0.016, "netIncomeToCommon": 391600000, "trailingEps": 0.09, "enterpriseToRevenue": 1.673, "enterpriseToEbitda": 7.982, "52WeekChange": -0.026315808, "SandP52WeekChange": 0.046755195, "lastDividendValue": 0.013, "lastDividendDate": 1663113600, "exchange": "PNK", "quoteType": "EQUITY", "symbol": "FPAFF", "underlyingSymbol": "FPAFF", "shortName": "FIRST PACIFIC CO", "longName": "First Pacific Company Limited", "firstTradeDateEpochUtc": 863184600, "timeZoneFullName": "America/New_York", "timeZoneShortName": "EDT", "uuid": "44122c90-1827-3e3b-8638-e4acf28c51d5", "messageBoardId": "finmb_410966", "gmtOffSetMilliseconds": -14400000, "currentPrice": 0.3653, "recommendationKey": "none", "totalCash": 2684699904, "totalCashPerShare": 0.634, "ebitda": 2160100096, "totalDebt": 11310499840, "quickRatio": 0.943, "currentRatio": 1.262, "totalRevenue": 10304900096, "debtToEquity": 109.114, "revenuePerShare": 2.421, "returnOnAssets": 0.04197, "returnOnEquity": 0.10005999, "grossProfits": 3056500000, "freeCashflow": -655587520, "operatingCashflow": 1424000000, "earningsGrowth": -0.003, "revenueGrowth": 0.073, "grossMargins": 0.29661, "ebitdaMargins": 0.20962, "operatingMargins": 0.16964, "financialCurrency": "USD", "trailingPegRatio": null}