{"address1": "233 South Wacker Drive", "city": "Chicago", "state": "IL", "zip": "60606-7147", "country": "United States", "phone": "312 621 6200", "website": "https://www.gatx.com", "industry": "Rental & Leasing Services", "industryDisp": "Rental & Leasing Services", "sector": "Industrials", "longBusinessSummary": "GATX Corporation, together its subsidiaries, operates as railcar leasing company in the United States, Canada, Mexico, Europe, and India. It operates through three segments: Rail North America, Rail International, and Portfolio Management. The company leases tank and freight railcars, and locomotives for petroleum, chemical, food/agriculture, and transportation industries. It also offers maintenance services, including the interior cleaning of railcars, routine maintenance and repair of car body and safety appliances, regulatory compliance works, wheelset replacements, interior blast and lining, exterior blast and painting, and car stenciling services. In addition, the company manufactures commercial aircraft jet engines and leases aircraft spare engines; and owns and manages tank containers that are leased to chemical, industrial gas, energy, food, cryogenic and pharmaceutical industries, and tank container operators, as well as provides tank container sourcing, remarketing, and inspection and maintenance services. As of December 31, 2022, it owned and operated a fleet of approximately 144,000 railcars; 501 four-axle and 43 six-axle locomotives; and 22,000 tank containers. GATX Corporation was founded in 1898 and is headquartered in Chicago, Illinois.", "fullTimeEmployees": 1904, "companyOfficers": [{"maxAge": 1, "name": "Mr. Robert C. Lyons", "age": 58, "title": "Pres, CEO & Director", "yearBorn": 1964, "fiscalYear": 2022, "totalPay": 1462952, "exercisedValue": 0, "unexercisedValue": 2739538}, {"maxAge": 1, "name": "Mr. Thomas A. Ellman", "age": 53, "title": "Exec. VP & CFO", "yearBorn": 1969, "fiscalYear": 2022, "totalPay": 998901, "exercisedValue": 1481238, "unexercisedValue": 2597105}, {"maxAge": 1, "name": "Ms. Kimberley  Nero", "age": 47, "title": "Exec. VP & Chief HR Officer", "yearBorn": 1975, "fiscalYear": 2022, "totalPay": 638108, "exercisedValue": 0, "unexercisedValue": 14543}, {"maxAge": 1, "name": "Mr. Robert A. Zmudka", "age": 54, "title": "Sr. VP & Chief Commercial Officer of Rail North America", "yearBorn": 1968, "fiscalYear": 2022, "totalPay": 613318, "exercisedValue": 183665, "unexercisedValue": 117632}, {"maxAge": 1, "name": "Mr. Paul F. Titterton", "age": 46, "title": "Exec. VP & Pres of Rail North America", "yearBorn": 1976, "fiscalYear": 2022, "totalPay": 864607, "exercisedValue": 419742, "unexercisedValue": 830967}, {"maxAge": 1, "name": "Ms. Jennifer M. McManus", "age": 42, "title": "Sr. VP, Controller & Chief Accounting Officer", "yearBorn": 1980, "exercisedValue": 0, "unexercisedValue": 0}, {"maxAge": 1, "name": "Mr. Niyi A. Adedoyin", "age": 54, "title": "Sr. VP & Chief Information Officer", "yearBorn": 1968, "exercisedValue": 0, "unexercisedValue": 0}, {"maxAge": 1, "name": "Ms. Shari  Hellerman", "title": "Sr. Director of Investor Relations, ESG & External Communications", "exercisedValue": 0, "unexercisedValue": 0}, {"maxAge": 1, "name": "Mr. Brian L. Glassberg", "age": 47, "title": "Exec. VP, Gen. Counsel & Corp. Sec.", "yearBorn": 1975, "exercisedValue": 0, "unexercisedValue": 0}, {"maxAge": 1, "name": "Mr. William J. Hasek", "age": 66, "title": "Sr. VP", "yearBorn": 1956, "fiscalYear": 2003, "exercisedValue": 0, "unexercisedValue": 0}], "auditRisk": 3, "boardRisk": 2, "compensationRisk": 5, "shareHolderRightsRisk": 2, "overallRisk": 2, "governanceEpochDate": 1682899200, "compensationAsOfEpochDate": 1672444800, "maxAge": 86400, "priceHint": 2, "previousClose": 112.08, "open": 113.06, "dayLow": 110.535, "dayHigh": 113.045, "regularMarketPreviousClose": 112.08, "regularMarketOpen": 113.06, "regularMarketDayLow": 110.535, "regularMarketDayHigh": 113.045, "dividendRate": 2.2, "dividendYield": 0.0196, "exDividendDate": 1686700800, "payoutRatio": 0.47849998, "fiveYearAvgDividendYield": 2.25, "beta": 1.062631, "trailingPE": 25.347727, "forwardPE": 16.187227, "volume": 75938, "regularMarketVolume": 75938, "averageVolume": 152778, "averageVolume10days": 142310, "averageDailyVolume10Day": 142310, "bid": 111.59, "ask": 114.14, "bidSize": 900, "askSize": 900, "marketCap": 3937008896, "fiftyTwoWeekLow": 84.96, "fiftyTwoWeekHigh": 118.11, "priceToSalesTrailing12Months": 3.0394573, "fiftyDayAverage": 109.0322, "twoHundredDayAverage": 104.98335, "trailingAnnualDividendRate": 2.11, "trailingAnnualDividendYield": 0.018825838, "currency": "USD", "enterpriseValue": 10420741120, "profitMargins": 0.12159, "floatShares": 35146835, "sharesOutstanding": 35300000, "sharesShort": 1806075, "sharesShortPriorMonth": 1647243, "sharesShortPreviousMonthDate": 1680220800, "dateShortInterest": 1682640000, "sharesPercentSharesOut": 0.0512, "heldPercentInsiders": 0.01079, "heldPercentInstitutions": 1.01716, "shortRatio": 13.54, "shortPercentOfFloat": 0.0856, "impliedSharesOutstanding": 0, "bookValue": 59.457, "priceToBook": 1.8758093, "lastFiscalYearEnd": 1672444800, "nextFiscalYearEnd": 1703980800, "mostRecentQuarter": 1680220800, "earningsQuarterlyGrowth": 0.021, "netIncomeToCommon": 157500000, "trailingEps": 4.4, "forwardEps": 6.89, "pegRatio": 1.35, "lastSplitFactor": "2:1", "lastSplitDate": 896745600, "enterpriseToRevenue": 8.045, "enterpriseToEbitda": 14.564, "52WeekChange": 0.06408429, "SandP52WeekChange": 0.046755195, "lastDividendValue": 0.55, "lastDividendDate": 1677715200, "exchange": "NYQ", "quoteType": "EQUITY", "symbol": "GATX", "underlyingSymbol": "GATX", "shortName": "GATX Corporation", "longName": "GATX Corporation", "firstTradeDateEpochUtc": 99153000, "timeZoneFullName": "America/New_York", "timeZoneShortName": "EDT", "uuid": "515b1ac1-d91c-352e-91ed-dcfc7f29a9fd", "messageBoardId": "finmb_176787", "gmtOffSetMilliseconds": -14400000, "currentPrice": 111.53, "targetHighPrice": 152.0, "targetLowPrice": 118.0, "targetMeanPrice": 132.0, "targetMedianPrice": 130.0, "recommendationMean": 1.8, "recommendationKey": "buy", "numberOfAnalystOpinions": 5, "totalCash": 177400000, "totalCashPerShare": 5.019, "ebitda": 715500032, "totalDebt": 6636700160, "quickRatio": 1.713, "currentRatio": 1.793, "totalRevenue": 1295299968, "debtToEquity": 315.808, "revenuePerShare": 36.642, "returnOnAssets": 0.02151, "returnOnEquity": 0.075679995, "grossProfits": 930100000, "freeCashflow": -830800000, "operatingCashflow": 528300000, "earningsGrowth": 0.029, "revenueGrowth": 0.07, "grossMargins": 0.72987, "ebitdaMargins": 0.55237997, "operatingMargins": 0.26511, "financialCurrency": "USD", "trailingPegRatio": null}